boombox.py
boombox-0.56.dist-info/LICENSE
boombox-0.56.dist-info/METADATA
boombox-0.56.dist-info/WHEEL
boombox-0.56.dist-info/top_level.txt
boombox-0.56.dist-info/RECORD
