Metadata-Version: 2.1
Name: boombox
Version: 0.56
Summary: A short, cross-platform, pure-python audio file  player and tone-generating module.
Home-page: https://github.com/mixmastamyk/boombox
Author: Mike Miller
Author-email: mixmastamyk@github.com
License: LGPLv3
Download-URL: https://github.com/mixmastamyk/boombox/get/default.tar.gz
Platform: UNKNOWN
Classifier: Development Status :: 3 - Alpha
Classifier: Intended Audience :: Developers
Classifier: License :: OSI Approved :: GNU Lesser General Public License v3 (LGPLv3)
Classifier: Operating System :: MacOS :: MacOS X
Classifier: Operating System :: Microsoft :: Windows
Classifier: Operating System :: POSIX :: Linux
Classifier: Programming Language :: Python
Classifier: Programming Language :: Python :: 3
Classifier: Topic :: Multimedia :: Sound/Audio
Classifier: Topic :: Multimedia :: Sound/Audio :: Players
Classifier: Topic :: Utilities
Requires-Python: >=3.6
Provides-Extra: mac
Provides-Extra: gstreamer
Provides-Extra: pyaudio
Provides-Extra: all
